codatsyncpayroll/__init__.py
codatsyncpayroll/accounts.py
codatsyncpayroll/companies.py
codatsyncpayroll/company_info.py
codatsyncpayroll/connections.py
codatsyncpayroll/journal_entries.py
codatsyncpayroll/journals.py
codatsyncpayroll/manage_data.py
codatsyncpayroll/sdk.py
codatsyncpayroll/sdkconfiguration.py
codatsyncpayroll/tracking_categories.py
codatsyncpayroll/models/__init__.py
codatsyncpayroll/models/errors/__init__.py
codatsyncpayroll/models/errors/errormessage.py
codatsyncpayroll/models/errors/sdkerror.py
codatsyncpayroll/models/operations/__init__.py
codatsyncpayroll/models/operations/create_account.py
codatsyncpayroll/models/operations/create_company.py
codatsyncpayroll/models/operations/create_connection.py
codatsyncpayroll/models/operations/create_journal.py
codatsyncpayroll/models/operations/create_journal_entry.py
codatsyncpayroll/models/operations/delete_company.py
codatsyncpayroll/models/operations/delete_connection.py
codatsyncpayroll/models/operations/delete_journal_entry.py
codatsyncpayroll/models/operations/get_account.py
codatsyncpayroll/models/operations/get_accounting_profile.py
codatsyncpayroll/models/operations/get_company.py
codatsyncpayroll/models/operations/get_connection.py
codatsyncpayroll/models/operations/get_create_accounts_model.py
codatsyncpayroll/models/operations/get_create_journal_model.py
codatsyncpayroll/models/operations/get_create_journalentry_model.py
codatsyncpayroll/models/operations/get_data_status.py
codatsyncpayroll/models/operations/get_journal.py
codatsyncpayroll/models/operations/get_journal_entry.py
codatsyncpayroll/models/operations/get_pull_operation.py
codatsyncpayroll/models/operations/get_push_operation.py
codatsyncpayroll/models/operations/get_tracking_category.py
codatsyncpayroll/models/operations/list_accounts.py
codatsyncpayroll/models/operations/list_companies.py
codatsyncpayroll/models/operations/list_connections.py
codatsyncpayroll/models/operations/list_journal_entries.py
codat_sync_for_payroll-3.0.0.dist-info/METADATA
codat_sync_for_payroll-3.0.0.dist-info/WHEEL
codat_sync_for_payroll-3.0.0.dist-info/top_level.txt
codat_sync_for_payroll-3.0.0.dist-info/RECORD
